{
  "schema_version": 3,
  "thread_key": "self-evolving/repo:pull_request:133:answer:default",
  "acpxRecordId": "019df42a-5949-7b83-8bd9-7f6bc651ccb0",
  "acpxSessionId": "019df42a-5949-7b83-8bd9-7f6bc651ccb0",
  "agentSessionId": "",
  "branch": "",
  "status": "running",
  "resume_status": "not_attempted",
  "last_resume_error": "",
  "resumed_from_session_id": "",
  "session_bundle_backend": "github-artifact",
  "session_bundle_artifact_id": "6798096939",
  "session_bundle_artifact_name": "session-bundle-pull_request-133-answer-default-dafab4711064-25355871761",
  "session_bundle_run_id": "25355871761",
  "bundle_restore_status": "restored",
  "last_bundle_restore_error": "",
  "forked_from_thread_key": "",
  "forked_from_acpx_session_id": "",
  "last_run_url": "https://github.com/self-evolving/repo/actions/runs/25488034936",
  "last_comment_url": "",
  "attempt_count": 3,
  "created_at": "2026-05-04T18:05:04.126Z",
  "updated_at": "2026-05-07T09:38:30.305Z"
}
