{
  "schema_version": 3,
  "thread_key": "self-evolving/repo:pull_request:3:fix-pr:fix-pr-codex",
  "acpxRecordId": "019dd2a2-f8e0-75b3-8818-e6cb0ce930bc",
  "acpxSessionId": "019dd2a3-03c2-70b0-90ab-9e0dda9145a3",
  "agentSessionId": "",
  "branch": "",
  "status": "completed",
  "resume_status": "resumed",
  "last_resume_error": "",
  "resumed_from_session_id": "019dd2a3-03c2-70b0-90ab-9e0dda9145a3",
  "session_bundle_backend": "github-artifact",
  "session_bundle_artifact_id": "6677262716",
  "session_bundle_artifact_name": "session-bundle-pull_request-3-fix-pr-fix-pr-codex-95fd19024173-25036586171",
  "session_bundle_run_id": "25036586171",
  "bundle_restore_status": "restored",
  "last_bundle_restore_error": "",
  "forked_from_thread_key": "",
  "forked_from_acpx_session_id": "",
  "last_run_url": "https://github.com/self-evolving/repo/actions/runs/25036586171",
  "last_comment_url": "",
  "attempt_count": 2,
  "created_at": "2026-04-28T05:49:45.204Z",
  "updated_at": "2026-04-28T06:03:04.439Z"
}
