{
  "author": {
    "id": "MDQ6VXNlcjIyNTEyODI1",
    "is_bot": false,
    "login": "lolipopshock",
    "name": "Shannon Shen"
  },
  "body": "@sepo-agent /answer\n\nCan you check --\n\n- Is the code working?  \n- or should we add a flag",
  "closedAt": null,
  "comments": [
    {
      "id": "IC_kwDOSOhEMM8AAAABAngHmA",
      "author": {
        "login": "lolipopshock"
      },
      "authorAssociation": "CONTRIBUTOR",
      "body": "@sepo-agent /answer \n\ntry again \n",
      "createdAt": "2026-04-28T14:48:16Z",
      "includesCreatedEdit": false,
      "isMinimized": false,
      "minimizedReason": "",
      "reactionGroups": [
        {
          "content": "EYES",
          "users": {
            "totalCount": 1
          }
        }
      ],
      "url": "https://github.com/self-evolving/repo/issues/5#issuecomment-4336387992",
      "viewerDidAuthor": false
    },
    {
      "id": "IC_kwDOSOhEMM8AAAABAn07yA",
      "author": {
        "login": "sepo-agent-app"
      },
      "authorAssociation": "NONE",
      "body": "I checked it again: the collapse path is already implemented and covered by tests, so this is not a “missing flag” case.\n\n- Old review syntheses are collapsed before posting a new one in [`post-comment.ts`](https://github.com/self-evolving/repo/blob/main/.agent/src/cli/post-comment.ts).\n- There is already a toggle: `AGENT_COLLAPSE_OLD_REVIEWS` (default behavior is enabled) in [`agent-review.yml`](https://github.com/self-evolving/repo/blob/main/.github/workflows/agent-review.yml).\n- The targeted test for this logic (`collapsePreviousReviewSummaries`) passes.\n\nSo: **no new flag needed**. If you still see old reviews not collapsing, the likely causes are:\n1. `AGENT_COLLAPSE_OLD_REVIEWS` is set to `false`/`0`/`off`, or  \n2. older comments were posted by a different bot identity and are filtered out by author match.",
      "createdAt": "2026-04-28T15:29:28Z",
      "includesCreatedEdit": false,
      "isMinimized": false,
      "minimizedReason": "",
      "reactionGroups": [],
      "url": "https://github.com/self-evolving/repo/issues/5#issuecomment-4336729032",
      "viewerDidAuthor": true
    }
  ],
  "createdAt": "2026-04-28T14:13:53Z",
  "labels": [],
  "number": 5,
  "state": "OPEN",
  "title": "Investigate why old reviews are not be collapsed",
  "updatedAt": "2026-04-28T15:29:28Z",
  "url": "https://github.com/self-evolving/repo/issues/5"
}
